alluxiofs/__init__.py
alluxiofs/core.py
alluxiofs/get_topic.py
alluxiofs/alluxioio/__init__.py
alluxiofs/alluxioio/alluxio_custom_io.py
alluxiofs/client/__init__.py
alluxiofs/client/cache.py
alluxiofs/client/config.py
alluxiofs/client/const.py
alluxiofs/client/core.py
alluxiofs/client/loadbalance.py
alluxiofs/client/prefetch_policy.py
alluxiofs/client/utils.py
benchmark/AbstractBench.py
benchmark/__init__.py
benchmark/ray_single_node_image_loader_microbenchmark.py
benchmark/bench/AlluxioFSSpecBench.py
benchmark/bench/AlluxioFSSpecTrafficBench.py
benchmark/bench/AlluxioRESTBench.py
benchmark/bench/RayBench.py
benchmark/bench/__init__.py
benchmark/bench/figure_plot.py
benchmark/bench/fsspec_stats.py
benchmark/bench/fuse_stats.py
benchmark/bench/postprocess.py
benchmark/bench/preprocess.py
alluxiofs-1.1.16.dist-info/LICENSE
alluxiofs-1.1.16.dist-info/METADATA
alluxiofs-1.1.16.dist-info/NOTICE
alluxiofs-1.1.16.dist-info/WHEEL
alluxiofs-1.1.16.dist-info/entry_points.txt
alluxiofs-1.1.16.dist-info/top_level.txt
alluxiofs-1.1.16.dist-info/RECORD
