Metadata-Version: 2.2
Name: alluxiofs
Version: 1.1.16
Summary: Alluxio Fsspec provides Alluxio filesystem spec implementation.
Home-page: https://github.com/fsspec/alluxiofs
Maintainer: Jiaming Mai, Xiaodong Yang, Lu Qiu
Maintainer-email: jiamingmai@163.com, xiaodong163831@gmail.com, luqiujob@gmail.com
Requires-Python: >=3.10
License-File: LICENSE
License-File: NOTICE
Requires-Dist: fsspec
Requires-Dist: aiohttp
Requires-Dist: decorator
Requires-Dist: humanfriendly
Requires-Dist: requests
Requires-Dist: etcd3
Requires-Dist: mmh3
Requires-Dist: sortedcontainers
Requires-Dist: pycurl
Requires-Dist: cachetools
Provides-Extra: tests
Requires-Dist: pytest; extra == "tests"
Requires-Dist: pytest-aiohttp; extra == "tests"
Requires-Dist: ray; extra == "tests"
Requires-Dist: pyarrow; extra == "tests"
Dynamic: description
Dynamic: description-content-type
Dynamic: home-page
Dynamic: maintainer
Dynamic: maintainer-email
Dynamic: provides-extra
Dynamic: requires-dist
Dynamic: requires-python
Dynamic: summary
